README.md
license.txt
pyproject.toml
src/cypherweb/__init__.py
src/cypherweb.egg-info/PKG-INFO
src/cypherweb.egg-info/SOURCES.txt
src/cypherweb.egg-info/dependency_links.txt
src/cypherweb.egg-info/requires.txt
src/cypherweb.egg-info/top_level.txt
src/cypherweb/core/__init__.py
src/cypherweb/core/graph.py
src/cypherweb/core/node.py
src/cypherweb/core/pipeline.py
src/cypherweb/nodes/__init__.py
src/cypherweb/nodes/cypher.py
src/cypherweb/nodes/html_to_graph.py
src/cypherweb/nodes/classifiers/__init__.py
src/cypherweb/nodes/classifiers/grids.py
src/cypherweb/nodes/classifiers/link.py
src/cypherweb/nodes/classifiers/link_list.py
src/cypherweb/nodes/classifiers/title.py
src/cypherweb/nodes/connectors/__init__.py
src/cypherweb/nodes/connectors/basic_crawler.py
src/cypherweb/nodes/enrichers/__init__.py
src/cypherweb/nodes/search/__init__.py
src/cypherweb/nodes/search/base.py
src/cypherweb/nodes/str_matchers/__init__.py
src/cypherweb/nodes/str_matchers/base.py
src/cypherweb/pipelines/__init__.py
src/cypherweb/utils/__init__.py
src/cypherweb/utils/html_to_graph.py
src/cypherweb/utils/visualizations.py